pyhighlight/__init__.py
pyhighlight-1.0.2.dist-info/METADATA
pyhighlight-1.0.2.dist-info/RECORD
pyhighlight-1.0.2.dist-info/WHEEL
pyhighlight-1.0.2.dist-info/top_level.txt
