Metadata-Version: 2.1
Name: pyhighlight
Version: 1.0.2
Summary: Tiny package to help highlight portions of an image with matplotlib
Home-page: https://github.com/iamtheburd/pyhighlight
Author: Tyler Burdsall
Author-email: tylerburdsall@gmail.com
License: UNKNOWN
Platform: UNKNOWN
